rawML/__init__.py
rawML/backend.py
rawML/layers.py
rawML/losses.py
rawML/optimizers.py
rawML-0.1.1.dist-info/LICENSE
rawML-0.1.1.dist-info/METADATA
rawML-0.1.1.dist-info/WHEEL
rawML-0.1.1.dist-info/top_level.txt
rawML-0.1.1.dist-info/RECORD
