Metadata-Version: 2.1
Name: rawML
Version: 0.1.1
Summary: Yet another ML library!
Home-page: https://github.com/TheAlphaJas/rawML-Python/
Author: Jasmer Singh Sanjotra
Author-email: jasmer.sanjotra@gmail.com
Classifier: Programming Language :: Python :: 3
Classifier: License :: OSI Approved :: MIT License
Classifier: Operating System :: OS Independent
Requires-Python: >=3.7
License-File: LICENSE
Requires-Dist: numpy
